ashpy/__init__.py
ashpy/ashtypes.py
ashpy/modes.py
ashpy/contexts/__init__.py
ashpy/contexts/base_context.py
ashpy/contexts/classifier.py
ashpy/contexts/gan.py
ashpy/datasets/__init__.py
ashpy/keras/__init__.py
ashpy/keras/losses.py
ashpy/layers/__init__.py
ashpy/layers/attention.py
ashpy/layers/instance_normalization.py
ashpy/losses/__init__.py
ashpy/losses/classifier.py
ashpy/losses/executor.py
ashpy/losses/gan.py
ashpy/metrics/__init__.py
ashpy/metrics/classifier.py
ashpy/metrics/gan.py
ashpy/metrics/metric.py
ashpy/metrics/sliced_wasserstein.py
ashpy/metrics/sliced_wasserstein_metric.py
ashpy/metrics/ssim_multiscale.py
ashpy/models/__init__.py
ashpy/models/gans.py
ashpy/models/convolutional/__init__.py
ashpy/models/convolutional/autoencoders.py
ashpy/models/convolutional/decoders.py
ashpy/models/convolutional/discriminators.py
ashpy/models/convolutional/encoders.py
ashpy/models/convolutional/interfaces.py
ashpy/models/convolutional/pix2pixhd.py
ashpy/models/convolutional/unet.py
ashpy/models/fc/__init__.py
ashpy/models/fc/autoencoders.py
ashpy/models/fc/decoders.py
ashpy/models/fc/encoders.py
ashpy/models/fc/interfaces.py
ashpy/trainers/__init__.py
ashpy/trainers/base_trainer.py
ashpy/trainers/classifier.py
ashpy/trainers/gan.py
ashpy-0.1.2.dist-info/LICENSE
ashpy-0.1.2.dist-info/METADATA
ashpy-0.1.2.dist-info/WHEEL
ashpy-0.1.2.dist-info/top_level.txt
ashpy-0.1.2.dist-info/RECORD
