Metadata-Version: 2.1
Name: ashpy
Version: 0.1.2
Summary: TensorFlow 2.0 library for distributed training, evaluation, model selection, and fast prototyping.
Home-page: https://github.com/zurutech/ashpy
Author: Machine Learning Team @ Zuru Tech
Author-email: ml@zuru.tech
License: Apache License, Version 2.0
Keywords: ashpy,ai,tensorflow,tensorflow-2.0,deeplearning
Platform: UNKNOWN
Classifier: Programming Language :: Python :: 3.7
Requires-Dist: numpy (>=1.16.3)
Requires-Dist: tensorflow-hub (>=0.4.0)
